{
	"version": "1.10.0",
	"surveyConfig": {
		"shortPeriodToRemind": 30,
		"longPeriodToRemind": 90,
		"popCoveragePercent": 0.1,
		"enabled": true,
		"daysLeftBeforeSurvey": 22,
		"surveyName": "userSatisfactionSurvey",
		"surveyUrl": "https://www.surveymonkey.com/r/6FJGVDV",
		"lastExtensionUsageDate": "2022-12-25T14:06:01.095Z"
	},
	"tipsConfig": {
		"daysLeftBeforeGeneralTip": 5,
		"firstTimeMinDaysToRemind": 4,
		"firstTimeMaxDaysToRemind": 6,
		"minDaysToRemind": 6,
		"maxDaysToRemind": 10,
		"daysAfterLastUsage": 30,
		"allTipsShownFirstly": false,
		"tips": {
			"generalTips": {
				"elementInspector": {},
				"logCatMonitor": {},
				"networkInspector": {
					"shownDate": "2022-12-25T14:06:00.804Z"
				},
				"directDebuggingWithHermes": {
					"shownDate": "2022-12-08T05:51:28.283Z"
				},
				"debuggingRNWAndMacOSApps": {
					"shownDate": "2022-12-15T14:30:25.246Z"
				},
				"expoHostType": {},
				"customEnvVariables": {}
			},
			"specificTips": {
				"networkInspectorLogsColorTheme": {}
			}
		},
		"lastExtensionUsageDate": "2022-12-25T14:06:00.804Z"
	}
}